kancylang.py
langeer.py
langeer-0.0.5.dist-info/METADATA
langeer-0.0.5.dist-info/WHEEL
langeer-0.0.5.dist-info/entry_points.txt
langeer-0.0.5.dist-info/top_level.txt
langeer-0.0.5.dist-info/RECORD
